{
  "schema_version": "1.0",
  "prediction_generated_at_utc": "2026-06-25T07:21:05.946780Z",
  "prediction_generated_at_local": "2026-06-25T15:21:05.946780+08:00",
  "quality_label": "ready",
  "match_id": "M60",
  "team_a": "Paraguay",
  "team_b": "Australia",
  "x_axis": {
    "field": "deviation",
    "domain": [
      0.0,
      1.0
    ],
    "label_cn": "比分偏离度（越大越激进）"
  },
  "y_axis": {
    "field": "probability",
    "label_cn": "最终概率"
  },
  "points": [
    {
      "score": "1-1",
      "deviation": 0.0,
      "probability": 0.15481481481481482,
      "probability_percent": 15.4815,
      "outcome": "draw",
      "sample_count": 418,
      "path_deviation": 0.6167690056343315,
      "result_surprise": 0.0,
      "reason_cn": "双方各有得分机会，但都难以形成持续优势。",
      "mechanism_ids": []
    },
    {
      "score": "1-0",
      "deviation": 0.045786946489481964,
      "probability": 0.1348148148148148,
      "probability_percent": 13.4815,
      "outcome": "team_a",
      "sample_count": 364,
      "path_deviation": 0.5754395905264129,
      "result_surprise": 0.12918660287081352,
      "reason_cn": "Paraguay在关键对位中略占上风，以一球优势收束比赛。",
      "mechanism_ids": []
    },
    {
      "score": "0-0",
      "deviation": 0.06895796913804171,
      "probability": 0.12962962962962962,
      "probability_percent": 12.963,
      "outcome": "draw",
      "sample_count": 350,
      "path_deviation": 0.5716924336646932,
      "result_surprise": 0.16267942583732065,
      "reason_cn": "双方防守结构有效，机会转化不足。",
      "mechanism_ids": []
    },
    {
      "score": "0-1",
      "deviation": 0.136904054034268,
      "probability": 0.11481481481481481,
      "probability_percent": 11.4815,
      "outcome": "team_b",
      "sample_count": 310,
      "path_deviation": 0.5620611196449035,
      "result_surprise": 0.2583732057416268,
      "reason_cn": "抢断后的快速转换；Australia通过压迫或转换取得一球优势。",
      "mechanism_ids": [
        "H_aus_transition_vs_paraguay_lines_02"
      ]
    },
    {
      "score": "1-2",
      "deviation": 0.4071507481984279,
      "probability": 0.06703703703703703,
      "probability_percent": 6.7037,
      "outcome": "team_b",
      "sample_count": 181,
      "path_deviation": 0.562521489413087,
      "result_surprise": 0.5669856459330144,
      "reason_cn": "边路突破与肋部防守对位；Australia通过压迫或转换取得一球优势。",
      "mechanism_ids": [
        "H_paraguay_wide_set_piece_vs_aus_rb_03"
      ]
    },
    {
      "score": "2-1",
      "deviation": 0.43666980492886004,
      "probability": 0.07407407407407407,
      "probability_percent": 7.4074,
      "outcome": "team_a",
      "sample_count": 200,
      "path_deviation": 0.6051987032071621,
      "result_surprise": 0.521531100478469,
      "reason_cn": "末轮出线收益压低前60分钟节奏，但巴拉圭真可接受平局存在、抢断后的快速转换；Paraguay在关键对位中略占上风，以一球优势收束比赛。",
      "mechanism_ids": [
        "H_late_draw_low_tempo_01",
        "H_almiron_absence_paraguay_attack_narrowing_04"
      ]
    },
    {
      "score": "2-0",
      "deviation": 0.436705233741377,
      "probability": 0.07,
      "probability_percent": 7.0,
      "outcome": "team_a",
      "sample_count": 189,
      "path_deviation": 0.5910505084139045,
      "result_surprise": 0.5478468899521531,
      "reason_cn": "末轮出线收益压低前60分钟节奏，但巴拉圭真可接受平局存在、抢断后的快速转换；Paraguay打破对方防守后扩大领先优势。",
      "mechanism_ids": [
        "H_late_draw_low_tempo_01",
        "H_almiron_absence_paraguay_attack_narrowing_04"
      ]
    },
    {
      "score": "0-2",
      "deviation": 0.5175290094411888,
      "probability": 0.04888888888888889,
      "probability_percent": 4.8889,
      "outcome": "team_b",
      "sample_count": 132,
      "path_deviation": 0.5674605293024729,
      "result_surprise": 0.6842105263157895,
      "reason_cn": "Australia充分兑现反击或进攻效率并扩大优势。",
      "mechanism_ids": []
    },
    {
      "score": "2-2",
      "deviation": 0.6122801566767457,
      "probability": 0.04185185185185185,
      "probability_percent": 4.1852,
      "outcome": "draw",
      "sample_count": 113,
      "path_deviation": 0.6014093291645171,
      "result_surprise": 0.729665071770335,
      "reason_cn": "比赛进入开放往返，双方进攻均有兑现。",
      "mechanism_ids": []
    },
    {
      "score": "3-1",
      "deviation": 0.6550264752266562,
      "probability": 0.03,
      "probability_percent": 3.0,
      "outcome": "team_a",
      "sample_count": 81,
      "path_deviation": 0.5865451192287101,
      "result_surprise": 0.80622009569378,
      "reason_cn": "抢断后的快速转换、边路突破与肋部防守对位；Paraguay打破对方防守后扩大领先优势。",
      "mechanism_ids": [
        "H_almiron_absence_paraguay_attack_narrowing_04",
        "H_paraguay_wide_set_piece_vs_aus_rb_03"
      ]
    },
    {
      "score": "3-2",
      "deviation": 0.6754899622931162,
      "probability": 0.01962962962962963,
      "probability_percent": 1.963,
      "outcome": "team_a",
      "sample_count": 53,
      "path_deviation": 0.563093877029271,
      "result_surprise": 0.8732057416267942,
      "reason_cn": "抢断后的快速转换、末轮出线收益压低前60分钟节奏，但巴拉圭真可接受平局存在；比赛被拉入高风险开放节奏，防线身后空间持续放大。",
      "mechanism_ids": [
        "H_aus_transition_vs_paraguay_lines_02",
        "H_late_draw_low_tempo_01"
      ]
    },
    {
      "score": "4-1",
      "deviation": 0.7027672088389249,
      "probability": 0.008148148148148147,
      "probability_percent": 0.8148,
      "outcome": "team_a",
      "sample_count": 22,
      "path_deviation": 0.5399794975818453,
      "result_surprise": 0.9473684210526316,
      "reason_cn": "抢断后的快速转换、边路突破与肋部防守对位；比赛被拉入高风险开放节奏，防线身后空间持续放大。",
      "mechanism_ids": [
        "H_almiron_absence_paraguay_attack_narrowing_04",
        "H_paraguay_wide_set_piece_vs_aus_rb_03"
      ]
    },
    {
      "score": "0-3",
      "deviation": 0.7223397221046588,
      "probability": 0.017407407407407406,
      "probability_percent": 1.7407,
      "outcome": "team_b",
      "sample_count": 47,
      "path_deviation": 0.5842527051567209,
      "result_surprise": 0.8875598086124402,
      "reason_cn": "抢断后的快速转换；Australia充分兑现反击或进攻效率并扩大优势。",
      "mechanism_ids": [
        "H_aus_transition_vs_paraguay_lines_02"
      ]
    },
    {
      "score": "3-0",
      "deviation": 0.7291100050833231,
      "probability": 0.014814814814814815,
      "probability_percent": 1.4815,
      "outcome": "team_a",
      "sample_count": 40,
      "path_deviation": 0.5794100179516495,
      "result_surprise": 0.9043062200956937,
      "reason_cn": "末轮出线收益压低前60分钟节奏，但巴拉圭真可接受平局存在、抢断后的快速转换；Paraguay打破对方防守后扩大领先优势。",
      "mechanism_ids": [
        "H_late_draw_low_tempo_01",
        "H_almiron_absence_paraguay_attack_narrowing_04"
      ]
    },
    {
      "score": "3-3",
      "deviation": 0.7321645365396846,
      "probability": 0.003703703703703704,
      "probability_percent": 0.3704,
      "outcome": "draw",
      "sample_count": 10,
      "path_deviation": 0.5426479018108367,
      "result_surprise": 0.9760765550239234,
      "reason_cn": "抢断后的快速转换、边路突破与肋部防守对位；比赛被拉入高风险开放节奏，防线身后空间持续放大。",
      "mechanism_ids": [
        "H_almiron_absence_paraguay_attack_narrowing_04",
        "H_paraguay_wide_set_piece_vs_aus_rb_03"
      ]
    },
    {
      "score": "5-1",
      "deviation": 0.7365022609837089,
      "probability": 0.0025925925925925925,
      "probability_percent": 0.2593,
      "outcome": "team_a",
      "sample_count": 7,
      "path_deviation": 0.5414580213180918,
      "result_surprise": 0.9832535885167464,
      "reason_cn": "抢断后的快速转换；比赛被拉入高风险开放节奏，防线身后空间持续放大。",
      "mechanism_ids": [
        "H_aus_transition_vs_paraguay_lines_02"
      ]
    },
    {
      "score": "1-3",
      "deviation": 0.7380486485355917,
      "probability": 0.021111111111111112,
      "probability_percent": 2.1111,
      "outcome": "team_b",
      "sample_count": 57,
      "path_deviation": 0.6068208113352275,
      "result_surprise": 0.8636363636363636,
      "reason_cn": "Australia充分兑现反击或进攻效率并扩大优势。",
      "mechanism_ids": []
    },
    {
      "score": "4-0",
      "deviation": 0.7726474771141633,
      "probability": 0.006666666666666667,
      "probability_percent": 0.6667,
      "outcome": "team_a",
      "sample_count": 18,
      "path_deviation": 0.5779154946432015,
      "result_surprise": 0.9569377990430622,
      "reason_cn": "抢断后的快速转换；Paraguay打破对方防守后扩大领先优势。",
      "mechanism_ids": [
        "H_aus_transition_vs_paraguay_lines_02"
      ]
    },
    {
      "score": "2-3",
      "deviation": 0.7908497100229925,
      "probability": 0.008518518518518519,
      "probability_percent": 0.8519,
      "outcome": "team_b",
      "sample_count": 23,
      "path_deviation": 0.5955800662841988,
      "result_surprise": 0.9449760765550239,
      "reason_cn": "比赛被拉入高风险开放节奏，防线身后空间持续放大。",
      "mechanism_ids": []
    },
    {
      "score": "1-6",
      "deviation": 0.8185991900612711,
      "probability": 0.00037037037037037035,
      "probability_percent": 0.037,
      "outcome": "team_b",
      "sample_count": 1,
      "path_deviation": 0.5843505393190752,
      "result_surprise": 0.9976076555023924,
      "reason_cn": "边路突破与肋部防守对位、抢断后的快速转换；比赛被拉入高风险开放节奏，防线身后空间持续放大。",
      "mechanism_ids": [
        "H_paraguay_wide_set_piece_vs_aus_rb_03",
        "H_almiron_absence_paraguay_attack_narrowing_04"
      ]
    },
    {
      "score": "5-4",
      "deviation": 0.8185991900612711,
      "probability": 0.00037037037037037035,
      "probability_percent": 0.037,
      "outcome": "team_a",
      "sample_count": 1,
      "path_deviation": 0.5843505393190752,
      "result_surprise": 0.9976076555023924,
      "reason_cn": "边路突破与肋部防守对位、抢断后的快速转换；比赛被拉入高风险开放节奏，防线身后空间持续放大。",
      "mechanism_ids": [
        "H_paraguay_wide_set_piece_vs_aus_rb_03",
        "H_almiron_absence_paraguay_attack_narrowing_04"
      ]
    },
    {
      "score": "5-0",
      "deviation": 0.829701881839313,
      "probability": 0.003703703703703704,
      "probability_percent": 0.3704,
      "outcome": "team_a",
      "sample_count": 10,
      "path_deviation": 0.6027902184272677,
      "result_surprise": 0.9760765550239234,
      "reason_cn": "末轮出线收益压低前60分钟节奏，但巴拉圭真可接受平局存在；比赛被拉入高风险开放节奏，防线身后空间持续放大。",
      "mechanism_ids": [
        "H_late_draw_low_tempo_01"
      ]
    },
    {
      "score": "1-4",
      "deviation": 0.832136912006934,
      "probability": 0.0033333333333333335,
      "probability_percent": 0.3333,
      "outcome": "team_b",
      "sample_count": 9,
      "path_deviation": 0.6030034922399788,
      "result_surprise": 0.9784688995215312,
      "reason_cn": "边路突破与肋部防守对位；比赛被拉入高风险开放节奏，防线身后空间持续放大。",
      "mechanism_ids": [
        "H_paraguay_wide_set_piece_vs_aus_rb_03"
      ]
    },
    {
      "score": "2-6",
      "deviation": 0.8811116755845064,
      "probability": 0.00037037037037037035,
      "probability_percent": 0.037,
      "outcome": "team_b",
      "sample_count": 1,
      "path_deviation": 0.6228962438927345,
      "result_surprise": 0.9976076555023924,
      "reason_cn": "抢断后的快速转换、末轮出线收益压低前60分钟节奏，但巴拉圭真可接受平局存在；比赛被拉入高风险开放节奏，防线身后空间持续放大。",
      "mechanism_ids": [
        "H_almiron_absence_paraguay_attack_narrowing_04",
        "H_late_draw_low_tempo_01"
      ]
    },
    {
      "score": "4-2",
      "deviation": 0.8855694913547296,
      "probability": 0.005185185185185185,
      "probability_percent": 0.5185,
      "outcome": "team_a",
      "sample_count": 14,
      "path_deviation": 0.6423913806631782,
      "result_surprise": 0.9665071770334929,
      "reason_cn": "抢断后的快速转换；比赛被拉入高风险开放节奏，防线身后空间持续放大。",
      "mechanism_ids": [
        "H_aus_transition_vs_paraguay_lines_02"
      ]
    },
    {
      "score": "0-4",
      "deviation": 0.904381323662681,
      "probability": 0.003703703703703704,
      "probability_percent": 0.3704,
      "outcome": "team_b",
      "sample_count": 10,
      "path_deviation": 0.6488381667395992,
      "result_surprise": 0.9760765550239234,
      "reason_cn": "抢断后的快速转换；Australia充分兑现反击或进攻效率并扩大优势。",
      "mechanism_ids": [
        "H_aus_transition_vs_paraguay_lines_02"
      ]
    },
    {
      "score": "3-4",
      "deviation": 0.9817956127165526,
      "probability": 0.001851851851851852,
      "probability_percent": 0.1852,
      "outcome": "team_b",
      "sample_count": 5,
      "path_deviation": 0.6901315164976026,
      "result_surprise": 0.9880382775119617,
      "reason_cn": "末轮出线收益压低前60分钟节奏，但巴拉圭真可接受平局存在、边路突破与肋部防守对位；比赛被拉入高风险开放节奏，防线身后空间持续放大。",
      "mechanism_ids": [
        "H_late_draw_low_tempo_01",
        "H_paraguay_wide_set_piece_vs_aus_rb_03"
      ]
    },
    {
      "score": "2-4",
      "deviation": 1.0,
      "probability": 0.0025925925925925925,
      "probability_percent": 0.2593,
      "outcome": "team_b",
      "sample_count": 7,
      "path_deviation": 0.7039328600472923,
      "result_surprise": 0.9832535885167464,
      "reason_cn": "比赛被拉入高风险开放节奏，防线身后空间持续放大。",
      "mechanism_ids": []
    },
    {
      "score": "2-5",
      "deviation": 1.0,
      "probability": 0.001851851851851852,
      "probability_percent": 0.1852,
      "outcome": "team_b",
      "sample_count": 5,
      "path_deviation": 0.7155788603654095,
      "result_surprise": 0.9880382775119617,
      "reason_cn": "比赛被拉入高风险开放节奏，防线身后空间持续放大。",
      "mechanism_ids": []
    },
    {
      "score": "3-5",
      "deviation": 1.0,
      "probability": 0.001851851851851852,
      "probability_percent": 0.1852,
      "outcome": "team_b",
      "sample_count": 5,
      "path_deviation": 0.7764393385691707,
      "result_surprise": 0.9880382775119617,
      "reason_cn": "边路突破与肋部防守对位；比赛被拉入高风险开放节奏，防线身后空间持续放大。",
      "mechanism_ids": [
        "H_paraguay_wide_set_piece_vs_aus_rb_03"
      ]
    },
    {
      "score": "0-5",
      "deviation": 1.0,
      "probability": 0.0014814814814814814,
      "probability_percent": 0.1481,
      "outcome": "team_b",
      "sample_count": 4,
      "path_deviation": 0.76810020532389,
      "result_surprise": 0.9904306220095693,
      "reason_cn": "比赛被拉入高风险开放节奏，防线身后空间持续放大。",
      "mechanism_ids": []
    },
    {
      "score": "1-5",
      "deviation": 1.0,
      "probability": 0.0014814814814814814,
      "probability_percent": 0.1481,
      "outcome": "team_b",
      "sample_count": 4,
      "path_deviation": 0.7236419359522243,
      "result_surprise": 0.9904306220095693,
      "reason_cn": "边路突破与肋部防守对位；比赛被拉入高风险开放节奏，防线身后空间持续放大。",
      "mechanism_ids": [
        "H_paraguay_wide_set_piece_vs_aus_rb_03"
      ]
    },
    {
      "score": "4-3",
      "deviation": 1.0,
      "probability": 0.0014814814814814814,
      "probability_percent": 0.1481,
      "outcome": "team_a",
      "sample_count": 4,
      "path_deviation": 0.864470306446733,
      "result_surprise": 0.9904306220095693,
      "reason_cn": "抢断后的快速转换、末轮出线收益压低前60分钟节奏，但巴拉圭真可接受平局存在；比赛被拉入高风险开放节奏，防线身后空间持续放大。",
      "mechanism_ids": [
        "H_almiron_absence_paraguay_attack_narrowing_04",
        "H_late_draw_low_tempo_01"
      ]
    },
    {
      "score": "5-2",
      "deviation": 1.0,
      "probability": 0.0011111111111111111,
      "probability_percent": 0.1111,
      "outcome": "team_a",
      "sample_count": 3,
      "path_deviation": 0.9207278722685793,
      "result_surprise": 0.992822966507177,
      "reason_cn": "边路突破与肋部防守对位；比赛被拉入高风险开放节奏，防线身后空间持续放大。",
      "mechanism_ids": [
        "H_paraguay_wide_set_piece_vs_aus_rb_03"
      ]
    },
    {
      "score": "0-7",
      "deviation": 1.0,
      "probability": 0.00037037037037037035,
      "probability_percent": 0.037,
      "outcome": "team_b",
      "sample_count": 1,
      "path_deviation": 0.9513119974019647,
      "result_surprise": 0.9976076555023924,
      "reason_cn": "抢断后的快速转换；比赛被拉入高风险开放节奏，防线身后空间持续放大。",
      "mechanism_ids": [
        "H_aus_transition_vs_paraguay_lines_02"
      ]
    },
    {
      "score": "6-2",
      "deviation": 1.0,
      "probability": 0.00037037037037037035,
      "probability_percent": 0.037,
      "outcome": "team_a",
      "sample_count": 1,
      "path_deviation": 1.0,
      "result_surprise": 0.9976076555023924,
      "reason_cn": "边路突破与肋部防守对位、抢断后的快速转换；比赛被拉入高风险开放节奏，防线身后空间持续放大。",
      "mechanism_ids": [
        "H_paraguay_wide_set_piece_vs_aus_rb_03",
        "H_almiron_absence_paraguay_attack_narrowing_04"
      ]
    }
  ],
  "recommended_encoding": {
    "x": "deviation",
    "y": "probability",
    "label": "score",
    "color": "outcome",
    "size": "probability"
  }
}