{
  "schema_version": "1.0",
  "phase": "normal_time",
  "rows": [
    {
      "score": "0-1",
      "probability": 0.16333333333333333,
      "goals_a": 0,
      "goals_b": 1
    },
    {
      "score": "0-2",
      "probability": 0.12777777777777777,
      "goals_a": 0,
      "goals_b": 2
    },
    {
      "score": "1-1",
      "probability": 0.1274074074074074,
      "goals_a": 1,
      "goals_b": 1
    },
    {
      "score": "0-0",
      "probability": 0.11222222222222222,
      "goals_a": 0,
      "goals_b": 0
    },
    {
      "score": "1-2",
      "probability": 0.08518518518518518,
      "goals_a": 1,
      "goals_b": 2
    }
  ]
}
